omnimalloc/_cpp.cpython-310-i386-linux-gnu.so
omnimalloc/visualize.py
omnimalloc/validate.py
omnimalloc/allocate.py
omnimalloc/py.typed
omnimalloc/_cpp.pyi
omnimalloc/__init__.py
omnimalloc/benchmark/utils.py
omnimalloc/benchmark/timer.py
omnimalloc/benchmark/benchmark.py
omnimalloc/benchmark/__init__.py
omnimalloc/benchmark/results/export.py
omnimalloc/benchmark/results/campaign.py
omnimalloc/benchmark/results/utils.py
omnimalloc/benchmark/results/visualize.py
omnimalloc/benchmark/results/report.py
omnimalloc/benchmark/results/__init__.py
omnimalloc/benchmark/results/result.py
omnimalloc/benchmark/sources/utils.py
omnimalloc/benchmark/sources/huggingface.py
omnimalloc/benchmark/sources/minimalloc.py
omnimalloc/benchmark/sources/generator.py
omnimalloc/benchmark/sources/__init__.py
omnimalloc/benchmark/sources/base.py
omnimalloc/benchmark/converters/onnx.py
omnimalloc/benchmark/converters/model.py
omnimalloc/benchmark/converters/__init__.py
omnimalloc/primitives/utils.py
omnimalloc/primitives/memory.py
omnimalloc/primitives/pool.py
omnimalloc/primitives/allocation.py
omnimalloc/primitives/__init__.py
omnimalloc/primitives/system.py
omnimalloc/common/directories.py
omnimalloc/common/units.py
omnimalloc/common/optional.py
omnimalloc/common/registry.py
omnimalloc/common/__init__.py
omnimalloc/allocators/utils.py
omnimalloc/allocators/random.py
omnimalloc/allocators/genetic.py
omnimalloc/allocators/greedy_cpp.py
omnimalloc/allocators/minimalloc.py
omnimalloc/allocators/hillclimb.py
omnimalloc/allocators/naive.py
omnimalloc/allocators/greedy.py
omnimalloc/allocators/__init__.py
omnimalloc/allocators/base.py
omnimalloc-0.2.0.dist-info/WHEEL
omnimalloc-0.2.0.dist-info/METADATA
omnimalloc-0.2.0.dist-info/RECORD
omnimalloc-0.2.0.dist-info/licenses/LICENSE
