Metadata-Version: 2.2
Name: omnimalloc
Version: 0.2.0
Summary: Your one-stop shop for static memory allocation.
Keywords: memory,allocation,allocator,static-allocation
Author-Email: Fabian Peddinghaus <fabianpedd@gmail.com>
License:                                  Apache License
Classifier: Development Status :: 4 - Beta
Classifier: Intended Audience :: Developers
Classifier: Intended Audience :: Science/Research
Classifier: License :: OSI Approved :: Apache Software License
Classifier: Operating System :: OS Independent
Classifier: Programming Language :: Python :: 3
Classifier: Programming Language :: Python :: 3.10
Classifier: Programming Language :: Python :: 3.11
Classifier: Programming Language :: Python :: 3.12
Classifier: Programming Language :: Python :: 3.13
Classifier: Programming Language :: C++
Classifier: Topic :: Scientific/Engineering
Classifier: Topic :: Software Development :: Libraries :: Python Modules
Classifier: Typing :: Typed
Project-URL: Homepage, https://github.com/fpedd/omnimalloc
Project-URL: Repository, https://github.com/fpedd/omnimalloc
Project-URL: Issues, https://github.com/fpedd/omnimalloc/issues
Requires-Python: >=3.10
Requires-Dist: numpy>=1.25.0
Requires-Dist: typing-extensions>=4.0.0
Provides-Extra: all
Requires-Dist: deap>=1.4.0; extra == "all"
Requires-Dist: huggingface-hub>=0.35.0; extra == "all"
Requires-Dist: matplotlib>=3.10.0; extra == "all"
Requires-Dist: onnx>=1.19.0; extra == "all"
Requires-Dist: tqdm>=4.66.0; extra == "all"
